adverity_json_parser/__init__.py
adverity_json_parser/parser.py
adverity_json_parser-1.0.0.dist-info/LICENSE
adverity_json_parser-1.0.0.dist-info/METADATA
adverity_json_parser-1.0.0.dist-info/WHEEL
adverity_json_parser-1.0.0.dist-info/top_level.txt
adverity_json_parser-1.0.0.dist-info/RECORD
