Metadata-Version: 2.1
Name: adverity-json-parser
Version: 1.0.0
Summary: Adverity json parser is a package created to parse json files on the adverity datastreams.
Home-page: https://github.com/devoteamgcloud/adverity-json-parser
Author: Nabil Lahssini | Jonas Ameye
Author-email: nabil.lahssini@devoteam.com
License: MIT
Classifier: License :: OSI Approved :: MIT License
Classifier: Programming Language :: Python :: 3
Classifier: Programming Language :: Python :: 3.9
License-File: LICENSE
Requires-Dist: requests
